{
  "envelope_standard": {
    "alpha_0.5": {
      "n_simulations": 500,
      "nominal_alpha": 0.5,
      "confidence_level": 0.5,
      "coverage_rate": 0.58,
      "coverage_se": 0.02207260745811423,
      "coverage_ci_lower": 0.5362894568035539,
      "coverage_ci_upper": 0.6224906487225976,
      "violation_rate_above": 0.154,
      "violation_rate_below": 0.36,
      "direction_test_pvalue": 1.1252883854659314e-10,
      "mean_band_area": 0.035339755987232296,
      "std_band_area": 0.01064982912879253,
      "mean_band_width": 0.035317943776672044,
      "width_percentiles": {
        "p10": 0.019560739355996233,
        "p50": 0.03657643456180945,
        "p90": 0.047719835755729176
      },
      "width_by_fpr_region": {
        "0-10": 0.05073593392238399,
        "10-30": 0.04350184789428816,
        "30-50": 0.03840179005602002,
        "50-70": 0.03214751171386242,
        "70-90": 0.026583861595630646,
        "90-100": 0.021637087248994442
      },
      "violation_rate_by_region": {
        "0-10": 0.258,
        "10-30": 0.036,
        "30-50": 0.04,
        "50-70": 0.052,
        "70-90": 0.1,
        "90-100": 0.242
      },
      "mean_max_violation": 0.003185297248769471,
      "percentile_95_max_violation": 0.01746762105485716
    },
    "alpha_0.05": {
      "n_simulations": 500,
      "nominal_alpha": 0.05,
      "confidence_level": 0.95,
      "coverage_rate": 0.628,
      "coverage_se": 0.021615549958305478,
      "coverage_ci_lower": 0.5848089173303663,
      "coverage_ci_upper": 0.6692392515114762,
      "violation_rate_above": 0.11,
      "violation_rate_below": 0.338,
      "direction_test_pvalue": 1.1265032695719679e-14,
      "mean_band_area": 0.04106844024194067,
      "std_band_area": 0.011690423615048743,
      "mean_band_width": 0.041044099302548,
      "width_percentiles": {
        "p10": 0.022482448235634066,
        "p50": 0.044620584187748426,
        "p90": 0.053080771585945416
      },
      "width_by_fpr_region": {
        "0-10": 0.059813931281402125,
        "10-30": 0.05233866163755063,
        "30-50": 0.045427474296607075,
        "50-70": 0.036555324186921125,
        "70-90": 0.02952867404663563,
        "90-100": 0.023448802789528215
      },
      "violation_rate_by_region": {
        "0-10": 0.222,
        "10-30": 0.014,
        "30-50": 0.018,
        "50-70": 0.048,
        "70-90": 0.084,
        "90-100": 0.22
      },
      "mean_max_violation": 0.002762662853149694,
      "percentile_95_max_violation": 0.017091490574335524
    }
  },
  "envelope_symmetric": {
    "alpha_0.5": {
      "n_simulations": 500,
      "nominal_alpha": 0.5,
      "confidence_level": 0.5,
      "coverage_rate": 0.432,
      "coverage_se": 0.022152923057691506,
      "coverage_ci_lower": 0.3892622537365845,
      "coverage_ci_upper": 0.47577465656618667,
      "violation_rate_above": 0.138,
      "violation_rate_below": 0.524,
      "direction_test_pvalue": 1.2897653321014758e-27,
      "mean_band_area": 0.030462902659740512,
      "std_band_area": 0.008734235980378587,
      "mean_band_width": 0.030438395699670363,
      "width_percentiles": {
        "p10": 0.01683596162277118,
        "p50": 0.032679155481446245,
        "p90": 0.03956007076951594
      },
      "width_by_fpr_region": {
        "0-10": 0.04470414046758547,
        "10-30": 0.03843927223964286,
        "30-50": 0.03341157502143085,
        "50-70": 0.027272829566478727,
        "70-90": 0.022147793502688407,
        "90-100": 0.017652586688062626
      },
      "violation_rate_by_region": {
        "0-10": 0.348,
        "10-30": 0.078,
        "30-50": 0.06,
        "50-70": 0.092,
        "70-90": 0.152,
        "90-100": 0.326
      },
      "mean_max_violation": 0.004197554728004079,
      "percentile_95_max_violation": 0.022187320799232465
    },
    "alpha_0.05": {
      "n_simulations": 500,
      "nominal_alpha": 0.05,
      "confidence_level": 0.95,
      "coverage_rate": 0.61,
      "coverage_se": 0.02181284025522582,
      "coverage_ci_lower": 0.566563975499563,
      "coverage_ci_upper": 0.6517586695988955,
      "violation_rate_above": 0.108,
      "violation_rate_below": 0.36,
      "direction_test_pvalue": 5.026161636909796e-17,
      "mean_band_area": 0.03882004552593925,
      "std_band_area": 0.011127599780764578,
      "mean_band_width": 0.03879473163306237,
      "width_percentiles": {
        "p10": 0.020735185527639356,
        "p50": 0.04207655483085933,
        "p90": 0.05067662706076448
      },
      "width_by_fpr_region": {
        "0-10": 0.05690631530313926,
        "10-30": 0.049876354792283265,
        "30-50": 0.04315765429226309,
        "50-70": 0.03436248587596417,
        "70-90": 0.027572714153051375,
        "90-100": 0.02164316379357717
      },
      "violation_rate_by_region": {
        "0-10": 0.238,
        "10-30": 0.014,
        "30-50": 0.018,
        "50-70": 0.05,
        "70-90": 0.084,
        "90-100": 0.232
      },
      "mean_max_violation": 0.002875511553351236,
      "percentile_95_max_violation": 0.01761432603386154
    }
  },
  "envelope_kde": {
    "alpha_0.5": {
      "n_simulations": 500,
      "nominal_alpha": 0.5,
      "confidence_level": 0.5,
      "coverage_rate": 0.578,
      "coverage_se": 0.02208691920571993,
      "coverage_ci_lower": 0.534276977868969,
      "coverage_ci_upper": 0.6205336250190289,
      "violation_rate_above": 0.156,
      "violation_rate_below": 0.362,
      "direction_test_pvalue": 1.3386947591195087e-10,
      "mean_band_area": 0.0353867743865717,
      "std_band_area": 0.010651144672856144,
      "mean_band_width": 0.03536497306186527,
      "width_percentiles": {
        "p10": 0.019593004382911835,
        "p50": 0.03671082145728023,
        "p90": 0.047719835755729176
      },
      "width_by_fpr_region": {
        "0-10": 0.05084056311450617,
        "10-30": 0.04359556237716237,
        "30-50": 0.03844176633609831,
        "50-70": 0.032180109519004824,
        "70-90": 0.026592465554356577,
        "90-100": 0.021652810749655475
      },
      "violation_rate_by_region": {
        "0-10": 0.26,
        "10-30": 0.04,
        "30-50": 0.038,
        "50-70": 0.05,
        "70-90": 0.098,
        "90-100": 0.242
      },
      "mean_max_violation": 0.003121115896779292,
      "percentile_95_max_violation": 0.017244880352989392
    },
    "alpha_0.05": {
      "n_simulations": 500,
      "nominal_alpha": 0.05,
      "confidence_level": 0.95,
      "coverage_rate": 0.654,
      "coverage_se": 0.021273645667821018,
      "coverage_ci_lower": 0.6112729349259212,
      "coverage_ci_upper": 0.6943787682119209,
      "violation_rate_above": 0.11,
      "violation_rate_below": 0.312,
      "direction_test_pvalue": 2.1870831434341212e-12,
      "mean_band_area": 0.04110185627304926,
      "std_band_area": 0.011705533589907708,
      "mean_band_width": 0.04107752449868863,
      "width_percentiles": {
        "p10": 0.022482559929659043,
        "p50": 0.04462198104942986,
        "p90": 0.053082948200350914
      },
      "width_by_fpr_region": {
        "0-10": 0.05993722232727135,
        "10-30": 0.05238000776275262,
        "30-50": 0.045457645218349996,
        "50-70": 0.03657082726633548,
        "70-90": 0.029539797462582586,
        "90-100": 0.023463331113556425
      },
      "violation_rate_by_region": {
        "0-10": 0.184,
        "10-30": 0.014,
        "30-50": 0.018,
        "50-70": 0.048,
        "70-90": 0.084,
        "90-100": 0.22
      },
      "mean_max_violation": 0.0020613316967938978,
      "percentile_95_max_violation": 0.012164198872963515
    }
  },
  "envelope_wilson": {
    "alpha_0.5": {
      "n_simulations": 500,
      "nominal_alpha": 0.5,
      "confidence_level": 0.5,
      "coverage_rate": 0.614,
      "coverage_se": 0.0217717247823869,
      "coverage_ci_lower": 0.5706131270887722,
      "coverage_ci_upper": 0.6556485232859939,
      "violation_rate_above": 0.126,
      "violation_rate_below": 0.31,
      "direction_test_pvalue": 3.938051337719437e-10,
      "mean_band_area": 0.03534212906480532,
      "std_band_area": 0.010649192415298528,
      "mean_band_width": 0.035320313078155856,
      "width_percentiles": {
        "p10": 0.01957091944539317,
        "p50": 0.03659607796995168,
        "p90": 0.047719835755729176
      },
      "width_by_fpr_region": {
        "0-10": 0.050731970891926895,
        "10-30": 0.04350201760347815,
        "30-50": 0.03840926305928826,
        "50-70": 0.03214811306512356,
        "70-90": 0.026586551537990572,
        "90-100": 0.021642943829357508
      },
      "violation_rate_by_region": {
        "0-10": 0.23,
        "10-30": 0.034,
        "30-50": 0.034,
        "50-70": 0.034,
        "70-90": 0.06,
        "90-100": 0.134
      },
      "mean_max_violation": 0.003178476137603286,
      "percentile_95_max_violation": 0.01746762105485716
    },
    "alpha_0.05": {
      "n_simulations": 500,
      "nominal_alpha": 0.05,
      "confidence_level": 0.95,
      "coverage_rate": 0.788,
      "coverage_se": 0.018278730809331373,
      "coverage_ci_lower": 0.7500478841824445,
      "coverage_ci_upper": 0.8215604957117015,
      "violation_rate_above": 0.04,
      "violation_rate_below": 0.174,
      "direction_test_pvalue": 3.796286088538813e-11,
      "mean_band_area": 0.04063794184977736,
      "std_band_area": 0.011514910513865282,
      "mean_band_width": 0.040613534368273176,
      "width_percentiles": {
        "p10": 0.022482448235634066,
        "p50": 0.04380059889535423,
        "p90": 0.05255228546642737
      },
      "width_by_fpr_region": {
        "0-10": 0.05927215288808913,
        "10-30": 0.051493227398347954,
        "30-50": 0.04471349499195814,
        "50-70": 0.03629308075892925,
        "70-90": 0.02945287775123119,
        "90-100": 0.023480245202125424
      },
      "violation_rate_by_region": {
        "0-10": 0.152,
        "10-30": 0.004,
        "30-50": 0.002,
        "50-70": 0.01,
        "70-90": 0.01,
        "90-100": 0.048
      },
      "mean_max_violation": 0.0027558062843112898,
      "percentile_95_max_violation": 0.017091490574335524
    }
  },
  "envelope_wilson_symmetric": {
    "alpha_0.5": {
      "n_simulations": 500,
      "nominal_alpha": 0.5,
      "confidence_level": 0.5,
      "coverage_rate": 0.47,
      "coverage_se": 0.022320394261750844,
      "coverage_ci_lower": 0.4266480518519465,
      "coverage_ci_upper": 0.5138094085757468,
      "violation_rate_above": 0.11,
      "violation_rate_below": 0.468,
      "direction_test_pvalue": 1.8930829466992554e-27,
      "mean_band_area": 0.030459620822811714,
      "std_band_area": 0.008733226902017823,
      "mean_band_width": 0.030435108275310485,
      "width_percentiles": {
        "p10": 0.01683596162277118,
        "p50": 0.032680999737290856,
        "p90": 0.03956007076951594
      },
      "width_by_fpr_region": {
        "0-10": 0.044692847149250446,
        "10-30": 0.0384272874032575,
        "30-50": 0.03340702172760666,
        "50-70": 0.027271820749998094,
        "70-90": 0.022150864272713663,
        "90-100": 0.017660048366544726
      },
      "violation_rate_by_region": {
        "0-10": 0.32,
        "10-30": 0.076,
        "30-50": 0.054,
        "50-70": 0.076,
        "70-90": 0.108,
        "90-100": 0.22
      },
      "mean_max_violation": 0.00419286342409904,
      "percentile_95_max_violation": 0.022187320799232465
    },
    "alpha_0.05": {
      "n_simulations": 500,
      "nominal_alpha": 0.05,
      "confidence_level": 0.95,
      "coverage_rate": 0.772,
      "coverage_se": 0.018762515822778138,
      "coverage_ci_lower": 0.7332341279039163,
      "coverage_ci_upper": 0.8066182308849994,
      "violation_rate_above": 0.038,
      "violation_rate_below": 0.194,
      "direction_test_pvalue": 8.630003120928982e-14,
      "mean_band_area": 0.03829462114661827,
      "std_band_area": 0.010942215243791251,
      "mean_band_width": 0.03826916027035106,
      "width_percentiles": {
        "p10": 0.02059616490849783,
        "p50": 0.04182288514008227,
        "p90": 0.04975559094715712
      },
      "width_by_fpr_region": {
        "0-10": 0.056219946968484494,
        "10-30": 0.048897686855013514,
        "30-50": 0.042343575993418696,
        "50-70": 0.033989656370878224,
        "70-90": 0.027453264660716056,
        "90-100": 0.021645752316225553
      },
      "violation_rate_by_region": {
        "0-10": 0.168,
        "10-30": 0.004,
        "30-50": 0.002,
        "50-70": 0.012,
        "70-90": 0.01,
        "90-100": 0.056
      },
      "mean_max_violation": 0.002966369144861784,
      "percentile_95_max_violation": 0.018855389864987474
    }
  },
  "envelope_logit": {
    "alpha_0.5": {
      "n_simulations": 500,
      "nominal_alpha": 0.5,
      "confidence_level": 0.5,
      "coverage_rate": 0.582,
      "coverage_se": 0.02205792374635473,
      "coverage_ci_lower": 0.5383026562362386,
      "coverage_ci_upper": 0.6244469519280668,
      "violation_rate_above": 0.3,
      "violation_rate_below": 0.3,
      "direction_test_pvalue": 1.0,
      "mean_band_area": 0.0369046912732755,
      "std_band_area": 0.010879478751195956,
      "mean_band_width": 0.03688331652395219,
      "width_percentiles": {
        "p10": 0.020312439297218043,
        "p50": 0.03886022420676696,
        "p90": 0.04938414491307654
      },
      "width_by_fpr_region": {
        "0-10": 0.05350223481460381,
        "10-30": 0.04575121322183078,
        "30-50": 0.04020751014785469,
        "50-70": 0.03341700034856796,
        "70-90": 0.027454952389121053,
        "90-100": 0.022126586656370562
      },
      "violation_rate_by_region": {
        "0-10": 0.26,
        "10-30": 0.026,
        "30-50": 0.034,
        "50-70": 0.056,
        "70-90": 0.102,
        "90-100": 0.298
      },
      "mean_max_violation": 0.002944898910893787,
      "percentile_95_max_violation": 0.017240938166249765
    },
    "alpha_0.05": {
      "n_simulations": 500,
      "nominal_alpha": 0.05,
      "confidence_level": 0.95,
      "coverage_rate": 0.604,
      "coverage_se": 0.02187162545399861,
      "coverage_ci_lower": 0.5604958406867544,
      "coverage_ci_upper": 0.6459182964972427,
      "violation_rate_above": 0.282,
      "violation_rate_below": 0.292,
      "direction_test_pvalue": 0.8133958458048124,
      "mean_band_area": 0.041218703992315114,
      "std_band_area": 0.01180141573711556,
      "mean_band_width": 0.04119446765803005,
      "width_percentiles": {
        "p10": 0.02247794955986742,
        "p50": 0.04456006562824272,
        "p90": 0.05319088230322291
      },
      "width_by_fpr_region": {
        "0-10": 0.06011772510494059,
        "10-30": 0.052486605069068486,
        "30-50": 0.04561330161552131,
        "50-70": 0.036690469246625904,
        "70-90": 0.029619750839114188,
        "90-100": 0.023526760035646174
      },
      "violation_rate_by_region": {
        "0-10": 0.25,
        "10-30": 0.014,
        "30-50": 0.022,
        "50-70": 0.05,
        "70-90": 0.096,
        "90-100": 0.284
      },
      "mean_max_violation": 0.0026747574507846703,
      "percentile_95_max_violation": 0.01648595208177097
    }
  },
  "envelope_symmetric_logit": {
    "alpha_0.5": {
      "n_simulations": 500,
      "nominal_alpha": 0.5,
      "confidence_level": 0.5,
      "coverage_rate": 0.426,
      "coverage_se": 0.02211442967837968,
      "coverage_ci_lower": 0.38338257836675194,
      "coverage_ci_upper": 0.46974582402155785,
      "violation_rate_above": 0.29,
      "violation_rate_below": 0.484,
      "direction_test_pvalue": 9.367631200685762e-07,
      "mean_band_area": 0.031066773288559366,
      "std_band_area": 0.009010708489625091,
      "mean_band_width": 0.031042416602053455,
      "width_percentiles": {
        "p10": 0.01675002035509946,
        "p50": 0.03355650195993884,
        "p90": 0.04085837377026263
      },
      "width_by_fpr_region": {
        "0-10": 0.045503428007456936,
        "10-30": 0.03928409755231091,
        "30-50": 0.034143635287657376,
        "50-70": 0.027758697602272033,
        "70-90": 0.022533550920248033,
        "90-100": 0.017994005839743775
      },
      "violation_rate_by_region": {
        "0-10": 0.38,
        "10-30": 0.082,
        "30-50": 0.058,
        "50-70": 0.092,
        "70-90": 0.152,
        "90-100": 0.366
      },
      "mean_max_violation": 0.004283112594857868,
      "percentile_95_max_violation": 0.02229161587644091
    },
    "alpha_0.05": {
      "n_simulations": 500,
      "nominal_alpha": 0.05,
      "confidence_level": 0.95,
      "coverage_rate": 0.584,
      "coverage_se": 0.02204286732709699,
      "coverage_ci_lower": 0.5403165775956056,
      "coverage_ci_upper": 0.6264025332068537,
      "violation_rate_above": 0.282,
      "violation_rate_below": 0.32,
      "direction_test_pvalue": 0.2994919523129301,
      "mean_band_area": 0.038854050497711054,
      "std_band_area": 0.011223681113028594,
      "mean_band_width": 0.03882874001802275,
      "width_percentiles": {
        "p10": 0.020534234137314755,
        "p50": 0.04201262501936766,
        "p90": 0.05087992523143496
      },
      "width_by_fpr_region": {
        "0-10": 0.05667643661706522,
        "10-30": 0.049728219214149404,
        "30-50": 0.04315730752496421,
        "50-70": 0.03444687439882755,
        "70-90": 0.027740073286652567,
        "90-100": 0.022005870047681585
      },
      "violation_rate_by_region": {
        "0-10": 0.268,
        "10-30": 0.018,
        "30-50": 0.022,
        "50-70": 0.052,
        "70-90": 0.1,
        "90-100": 0.296
      },
      "mean_max_violation": 0.0028991238759342236,
      "percentile_95_max_violation": 0.017555890769551802
    }
  },
  "envelope_wilson_logit": {
    "alpha_0.5": {
      "n_simulations": 500,
      "nominal_alpha": 0.5,
      "confidence_level": 0.5,
      "coverage_rate": 0.342,
      "coverage_se": 0.021214900423994452,
      "coverage_ci_lower": 0.3017655066658599,
      "coverage_ci_upper": 0.38464378491999074,
      "violation_rate_above": 0.466,
      "violation_rate_below": 0.428,
      "direction_test_pvalue": 0.3945879461467612,
      "mean_band_area": 0.025409998277673825,
      "std_band_area": 0.007409815769595477,
      "mean_band_width": 0.025381947969614797,
      "width_percentiles": {
        "p10": 0.013550970948536554,
        "p50": 0.027356460808514706,
        "p90": 0.0337858906421519
      },
      "width_by_fpr_region": {
        "0-10": 0.03740893920609192,
        "10-30": 0.032298423643202984,
        "30-50": 0.028050321998894213,
        "50-70": 0.022653792734861376,
        "70-90": 0.01825689741885662,
        "90-100": 0.01447448997559424
      },
      "violation_rate_by_region": {
        "0-10": 0.424,
        "10-30": 0.102,
        "30-50": 0.09,
        "50-70": 0.122,
        "70-90": 0.168,
        "90-100": 0.452
      },
      "mean_max_violation": 0.00472850611501768,
      "percentile_95_max_violation": 0.02340445783393768
    },
    "alpha_0.05": {
      "n_simulations": 500,
      "nominal_alpha": 0.05,
      "confidence_level": 0.95,
      "coverage_rate": 0.566,
      "coverage_se": 0.02216501748251059,
      "coverage_ci_lower": 0.5222171596922527,
      "coverage_ci_upper": 0.6087764273668224,
      "violation_rate_above": 0.306,
      "violation_rate_below": 0.308,
      "direction_test_pvalue": 1.0,
      "mean_band_area": 0.036942626180949234,
      "std_band_area": 0.010621908473407873,
      "mean_band_width": 0.03691480965990601,
      "width_percentiles": {
        "p10": 0.020050016136783724,
        "p50": 0.03967360198605082,
        "p90": 0.048614565051639504
      },
      "width_by_fpr_region": {
        "0-10": 0.053859428785227474,
        "10-30": 0.047210800414991684,
        "30-50": 0.04097672167048603,
        "50-70": 0.03289884187424182,
        "70-90": 0.026443092568993565,
        "90-100": 0.020818278240110583
      },
      "violation_rate_by_region": {
        "0-10": 0.268,
        "10-30": 0.02,
        "30-50": 0.026,
        "50-70": 0.052,
        "70-90": 0.096,
        "90-100": 0.31
      },
      "mean_max_violation": 0.003040162781987417,
      "percentile_95_max_violation": 0.01904386823202037
    }
  },
  "envelope_wilson_symmetric_logit": {
    "alpha_0.5": {
      "n_simulations": 500,
      "nominal_alpha": 0.5,
      "confidence_level": 0.5,
      "coverage_rate": 0.356,
      "coverage_se": 0.021413266915629666,
      "coverage_ci_lower": 0.3152745600260401,
      "coverage_ci_upper": 0.398921250026887,
      "violation_rate_above": 0.4,
      "violation_rate_below": 0.476,
      "direction_test_pvalue": 0.07695323879600063,
      "mean_band_area": 0.02547772004463328,
      "std_band_area": 0.007597569100743084,
      "mean_band_width": 0.025449224163446603,
      "width_percentiles": {
        "p10": 0.013384748424475469,
        "p50": 0.027327661332654532,
        "p90": 0.03427559933083256
      },
      "width_by_fpr_region": {
        "0-10": 0.03769078609046247,
        "10-30": 0.03248375741310045,
        "30-50": 0.028137391404479743,
        "50-70": 0.022658798514723782,
        "70-90": 0.01821972960114479,
        "90-100": 0.014394129490186114
      },
      "violation_rate_by_region": {
        "0-10": 0.422,
        "10-30": 0.102,
        "30-50": 0.082,
        "50-70": 0.114,
        "70-90": 0.166,
        "90-100": 0.442
      },
      "mean_max_violation": 0.004828906858009788,
      "percentile_95_max_violation": 0.02386527513603937
    },
    "alpha_0.05": {
      "n_simulations": 500,
      "nominal_alpha": 0.05,
      "confidence_level": 0.95,
      "coverage_rate": 0.566,
      "coverage_se": 0.02216501748251059,
      "coverage_ci_lower": 0.5222171596922527,
      "coverage_ci_upper": 0.6087764273668224,
      "violation_rate_above": 0.304,
      "violation_rate_below": 0.314,
      "direction_test_pvalue": 0.8200399650517363,
      "mean_band_area": 0.036606178654177424,
      "std_band_area": 0.010734541573555677,
      "mean_band_width": 0.03657812819027881,
      "width_percentiles": {
        "p10": 0.019584307025065063,
        "p50": 0.03944069924612499,
        "p90": 0.04868922823955102
      },
      "width_by_fpr_region": {
        "0-10": 0.053405983358268856,
        "10-30": 0.04676971690344007,
        "30-50": 0.040612220679037275,
        "50-70": 0.032609825658321386,
        "70-90": 0.026182279332757,
        "90-100": 0.020620138654451885
      },
      "violation_rate_by_region": {
        "0-10": 0.274,
        "10-30": 0.022,
        "30-50": 0.024,
        "50-70": 0.054,
        "70-90": 0.098,
        "90-100": 0.308
      },
      "mean_max_violation": 0.003114831775570044,
      "percentile_95_max_violation": 0.020023317748832193
    }
  },
  "envelope_kde_logit": {
    "alpha_0.5": {
      "n_simulations": 500,
      "nominal_alpha": 0.5,
      "confidence_level": 0.5,
      "coverage_rate": 0.584,
      "coverage_se": 0.02204286732709699,
      "coverage_ci_lower": 0.5403165775956056,
      "coverage_ci_upper": 0.6264025332068537,
      "violation_rate_above": 0.3,
      "violation_rate_below": 0.298,
      "direction_test_pvalue": 1.0,
      "mean_band_area": 0.0366860516131289,
      "std_band_area": 0.010984476268950008,
      "mean_band_width": 0.036664634727127866,
      "width_percentiles": {
        "p10": 0.019915596510194783,
        "p50": 0.038543816590988836,
        "p90": 0.04938414491307654
      },
      "width_by_fpr_region": {
        "0-10": 0.05328281868608063,
        "10-30": 0.0453247948572496,
        "30-50": 0.039843850762337436,
        "50-70": 0.03326473020970821,
        "70-90": 0.027414736295104027,
        "90-100": 0.02212472188211011
      },
      "violation_rate_by_region": {
        "0-10": 0.26,
        "10-30": 0.03,
        "30-50": 0.036,
        "50-70": 0.064,
        "70-90": 0.104,
        "90-100": 0.296
      },
      "mean_max_violation": 0.002961954759004184,
      "percentile_95_max_violation": 0.017240938166249765
    },
    "alpha_0.05": {
      "n_simulations": 500,
      "nominal_alpha": 0.05,
      "confidence_level": 0.95,
      "coverage_rate": 0.604,
      "coverage_se": 0.02187162545399861,
      "coverage_ci_lower": 0.5604958406867544,
      "coverage_ci_upper": 0.6459182964972427,
      "violation_rate_above": 0.282,
      "violation_rate_below": 0.29,
      "direction_test_pvalue": 0.8592386636896292,
      "mean_band_area": 0.04110556857671922,
      "std_band_area": 0.011756827203384376,
      "mean_band_width": 0.04108133441082679,
      "width_percentiles": {
        "p10": 0.02247794955986742,
        "p50": 0.04442312372138582,
        "p90": 0.05307342848910239
      },
      "width_by_fpr_region": {
        "0-10": 0.05990028537415084,
        "10-30": 0.052299494907694054,
        "30-50": 0.045478500591441984,
        "50-70": 0.03658530962240696,
        "70-90": 0.02959027074110508,
        "90-100": 0.023525701592306415
      },
      "violation_rate_by_region": {
        "0-10": 0.25,
        "10-30": 0.014,
        "30-50": 0.022,
        "50-70": 0.052,
        "70-90": 0.096,
        "90-100": 0.284
      },
      "mean_max_violation": 0.0026746918946828502,
      "percentile_95_max_violation": 0.01648595208177097
    }
  },
  "envelope_kde_symmetric_logit": {
    "alpha_0.5": {
      "n_simulations": 500,
      "nominal_alpha": 0.5,
      "confidence_level": 0.5,
      "coverage_rate": 0.428,
      "coverage_se": 0.022127629787213995,
      "coverage_ci_lower": 0.38534175538940585,
      "coverage_ci_upper": 0.4717561496370578,
      "violation_rate_above": 0.29,
      "violation_rate_below": 0.476,
      "direction_test_pvalue": 2.3236217169589163e-06,
      "mean_band_area": 0.03070341500557802,
      "std_band_area": 0.009037871217347533,
      "mean_band_width": 0.03067898575287773,
      "width_percentiles": {
        "p10": 0.016550576804899936,
        "p50": 0.032734639888408926,
        "p90": 0.04092321488445978
      },
      "width_by_fpr_region": {
        "0-10": 0.044945993005636384,
        "10-30": 0.038643861698289865,
        "30-50": 0.033624323750659824,
        "50-70": 0.027486987421393393,
        "70-90": 0.02242746641290188,
        "90-100": 0.01799254389437373
      },
      "violation_rate_by_region": {
        "0-10": 0.386,
        "10-30": 0.086,
        "30-50": 0.062,
        "50-70": 0.098,
        "70-90": 0.152,
        "90-100": 0.356
      },
      "mean_max_violation": 0.004379923431605142,
      "percentile_95_max_violation": 0.023194237037068497
    },
    "alpha_0.05": {
      "n_simulations": 500,
      "nominal_alpha": 0.05,
      "confidence_level": 0.95,
      "coverage_rate": 0.586,
      "coverage_se": 0.0220274374360705,
      "coverage_ci_lower": 0.5423312223504144,
      "coverage_ci_upper": 0.6283573910901985,
      "violation_rate_above": 0.282,
      "violation_rate_below": 0.312,
      "direction_test_pvalue": 0.4166288108884334,
      "mean_band_area": 0.038577746418242596,
      "std_band_area": 0.01122708773718042,
      "mean_band_width": 0.038552380786684166,
      "width_percentiles": {
        "p10": 0.0204555243581599,
        "p50": 0.04189148221845316,
        "p90": 0.050639353466293696
      },
      "width_by_fpr_region": {
        "0-10": 0.055888670833117556,
        "10-30": 0.04921996764508123,
        "30-50": 0.04285193840335309,
        "50-70": 0.034310025683641436,
        "70-90": 0.0276901271122694,
        "90-100": 0.02203137398979621
      },
      "violation_rate_by_region": {
        "0-10": 0.268,
        "10-30": 0.018,
        "30-50": 0.022,
        "50-70": 0.054,
        "70-90": 0.098,
        "90-100": 0.29
      },
      "mean_max_violation": 0.003030718868615364,
      "percentile_95_max_violation": 0.019846962500751717
    }
  },
  "HT_log_concave": {
    "alpha_0.5": {
      "n_simulations": 500,
      "nominal_alpha": 0.5,
      "confidence_level": 0.5,
      "coverage_rate": 0.434,
      "coverage_se": 0.02216501748251059,
      "coverage_ci_lower": 0.3912235726331776,
      "coverage_ci_upper": 0.47778284030774737,
      "violation_rate_above": 0.222,
      "violation_rate_below": 0.476,
      "direction_test_pvalue": 9.111256955000888e-12,
      "mean_band_area": 0.031125430492908782,
      "std_band_area": 0.009621378790215714,
      "mean_band_width": 0.03113185686428164,
      "width_percentiles": {
        "p10": 0.01697960153749691,
        "p50": 0.033217987863510504,
        "p90": 0.039828777333084625
      },
      "width_by_fpr_region": {
        "0-10": 0.047959040065089185,
        "10-30": 0.04019277851417709,
        "30-50": 0.03372442552135885,
        "50-70": 0.02708800273311138,
        "70-90": 0.021871934683442115,
        "90-100": 0.017507966027764266
      },
      "violation_rate_by_region": {
        "0-10": 0.352,
        "10-30": 0.046,
        "30-50": 0.034,
        "50-70": 0.06,
        "70-90": 0.122,
        "90-100": 0.342
      },
      "mean_max_violation": 0.0040355403755562335,
      "percentile_95_max_violation": 0.021041042603307778
    },
    "alpha_0.05": {
      "n_simulations": 500,
      "nominal_alpha": 0.05,
      "confidence_level": 0.95,
      "coverage_rate": 0.574,
      "coverage_se": 0.02211442967837968,
      "coverage_ci_lower": 0.5302541759784422,
      "coverage_ci_upper": 0.616617421633248,
      "violation_rate_above": 0.162,
      "violation_rate_below": 0.366,
      "direction_test_pvalue": 3.0899443887276424e-10,
      "mean_band_area": 0.039128443165676985,
      "std_band_area": 0.012102513332110175,
      "mean_band_width": 0.03913647045976893,
      "width_percentiles": {
        "p10": 0.021350105213246172,
        "p50": 0.04176847308808552,
        "p90": 0.05008025778604311
      },
      "width_by_fpr_region": {
        "0-10": 0.060280998180292804,
        "10-30": 0.0505372135521318,
        "30-50": 0.04240297125530242,
        "50-70": 0.03405594616007805,
        "70-90": 0.027493958293557167,
        "90-100": 0.021981292369598875
      },
      "violation_rate_by_region": {
        "0-10": 0.232,
        "10-30": 0.022,
        "30-50": 0.02,
        "50-70": 0.05,
        "70-90": 0.088,
        "90-100": 0.278
      },
      "mean_max_violation": 0.00221145618139301,
      "percentile_95_max_violation": 0.0137667590920124
    }
  },
  "HT_log_concave_calib": {
    "alpha_0.5": {
      "n_simulations": 500,
      "nominal_alpha": 0.5,
      "confidence_level": 0.5,
      "coverage_rate": 0.436,
      "coverage_se": 0.02217674457624473,
      "coverage_ci_lower": 0.39318560312305606,
      "coverage_ci_upper": 0.47979031245602277,
      "violation_rate_above": 0.22,
      "violation_rate_below": 0.482,
      "direction_test_pvalue": 2.207684522755078e-12,
      "mean_band_area": 0.03160517821817395,
      "std_band_area": 0.011577058739197633,
      "mean_band_width": 0.031611700558285605,
      "width_percentiles": {
        "p10": 0.015792350486221973,
        "p50": 0.03250179149003285,
        "p90": 0.0434109496505813
      },
      "width_by_fpr_region": {
        "0-10": 0.04804423652797045,
        "10-30": 0.040591875148762606,
        "30-50": 0.03428730037687718,
        "50-70": 0.027627458225131032,
        "70-90": 0.02244411691045761,
        "90-100": 0.018071900530251674
      },
      "violation_rate_by_region": {
        "0-10": 0.348,
        "10-30": 0.046,
        "30-50": 0.04,
        "50-70": 0.072,
        "70-90": 0.106,
        "90-100": 0.35
      },
      "mean_max_violation": 0.0040853132818844725,
      "percentile_95_max_violation": 0.022893403399452564
    },
    "alpha_0.05": {
      "n_simulations": 500,
      "nominal_alpha": 0.05,
      "confidence_level": 0.95,
      "coverage_rate": 0.664,
      "coverage_se": 0.02112363605064242,
      "coverage_ci_lower": 0.62148722415566,
      "coverage_ci_upper": 0.704011992172951,
      "violation_rate_above": 0.12,
      "violation_rate_below": 0.31,
      "direction_test_pvalue": 7.124460202999853e-11,
      "mean_band_area": 0.051624999747274615,
      "std_band_area": 0.02044216233151817,
      "mean_band_width": 0.051635526852645136,
      "width_percentiles": {
        "p10": 0.025530812971580462,
        "p50": 0.05157488003554976,
        "p90": 0.07361278024362196
      },
      "width_by_fpr_region": {
        "0-10": 0.08048871284817875,
        "10-30": 0.06659385612107355,
        "30-50": 0.055651685847744346,
        "50-70": 0.04469829055070878,
        "70-90": 0.03629975743925572,
        "90-100": 0.02921766936826611
      },
      "violation_rate_by_region": {
        "0-10": 0.17,
        "10-30": 0.012,
        "30-50": 0.016,
        "50-70": 0.046,
        "70-90": 0.084,
        "90-100": 0.234
      },
      "mean_max_violation": 0.0011174852758469816,
      "percentile_95_max_violation": 0.0055012260588911425
    }
  },
  "HT_reflected_kde": {
    "alpha_0.5": {
      "n_simulations": 500,
      "nominal_alpha": 0.5,
      "confidence_level": 0.5,
      "coverage_rate": 0.378,
      "coverage_se": 0.02168483340955148,
      "coverage_ci_lower": 0.3365807935394356,
      "coverage_ci_upper": 0.42127954553318325,
      "violation_rate_above": 0.242,
      "violation_rate_below": 0.484,
      "direction_test_pvalue": 2.062478345632332e-10,
      "mean_band_area": 0.031428733545347656,
      "std_band_area": 0.00889156979866945,
      "mean_band_width": 0.03143502054945754,
      "width_percentiles": {
        "p10": 0.017595433984357946,
        "p50": 0.03394881842971167,
        "p90": 0.040261187199784734
      },
      "width_by_fpr_region": {
        "0-10": 0.04479160880026173,
        "10-30": 0.039262421622326724,
        "30-50": 0.034292157497771085,
        "50-70": 0.027845499845504763,
        "70-90": 0.02305558858990669,
        "90-100": 0.02054330493233161
      },
      "violation_rate_by_region": {
        "0-10": 0.436,
        "10-30": 0.034,
        "30-50": 0.024,
        "50-70": 0.046,
        "70-90": 0.084,
        "90-100": 0.258
      },
      "mean_max_violation": 0.006038250780491772,
      "percentile_95_max_violation": 0.028245177527417842
    },
    "alpha_0.05": {
      "n_simulations": 500,
      "nominal_alpha": 0.05,
      "confidence_level": 0.95,
      "coverage_rate": 0.562,
      "coverage_se": 0.022188104921331157,
      "coverage_ci_lower": 0.5182029258694332,
      "coverage_ci_upper": 0.6048516559133346,
      "violation_rate_above": 0.16,
      "violation_rate_below": 0.34,
      "direction_test_pvalue": 1.276019064584565e-08,
      "mean_band_area": 0.03951142683280002,
      "std_band_area": 0.011180382049481427,
      "mean_band_width": 0.03951933069893981,
      "width_percentiles": {
        "p10": 0.022120485388474314,
        "p50": 0.042678528895606194,
        "p90": 0.05062397411428459
      },
      "width_by_fpr_region": {
        "0-10": 0.056304271071382826,
        "10-30": 0.04936577480200461,
        "30-50": 0.04311609713383019,
        "50-70": 0.035007184704184534,
        "70-90": 0.02898191030049324,
        "90-100": 0.025816430514563102
      },
      "violation_rate_by_region": {
        "0-10": 0.28,
        "10-30": 0.018,
        "30-50": 0.01,
        "50-70": 0.034,
        "70-90": 0.052,
        "90-100": 0.156
      },
      "mean_max_violation": 0.0036882870234337074,
      "percentile_95_max_violation": 0.019811103599333912
    }
  },
  "HT_kde": {
    "alpha_0.5": {
      "n_simulations": 500,
      "nominal_alpha": 0.5,
      "confidence_level": 0.5,
      "coverage_rate": 0.376,
      "coverage_se": 0.021662132858977667,
      "coverage_ci_lower": 0.3346400158192325,
      "coverage_ci_upper": 0.4192508206152326,
      "violation_rate_above": 0.262,
      "violation_rate_below": 0.508,
      "direction_test_pvalue": 3.603171140352999e-10,
      "mean_band_area": 0.030700602764282613,
      "std_band_area": 0.008716458761457702,
      "mean_band_width": 0.030706744113105238,
      "width_percentiles": {
        "p10": 0.016805207951113232,
        "p50": 0.03342401268935771,
        "p90": 0.0395879275686957
      },
      "width_by_fpr_region": {
        "0-10": 0.04395024077472718,
        "10-30": 0.039243990962738104,
        "30-50": 0.03403643128169327,
        "50-70": 0.027393081212878225,
        "70-90": 0.02212658155488968,
        "90-100": 0.01742077529311418
      },
      "violation_rate_by_region": {
        "0-10": 0.442,
        "10-30": 0.034,
        "30-50": 0.03,
        "50-70": 0.058,
        "70-90": 0.118,
        "90-100": 0.352
      },
      "mean_max_violation": 0.005427618069634551,
      "percentile_95_max_violation": 0.026289027027137594
    },
    "alpha_0.05": {
      "n_simulations": 500,
      "nominal_alpha": 0.05,
      "confidence_level": 0.95,
      "coverage_rate": 0.536,
      "coverage_se": 0.022302645582979612,
      "coverage_ci_lower": 0.492179234494295,
      "coverage_ci_upper": 0.5792718129924732,
      "violation_rate_above": 0.186,
      "violation_rate_below": 0.388,
      "direction_test_pvalue": 2.4684497522614163e-09,
      "mean_band_area": 0.038595968515759325,
      "std_band_area": 0.01096417160793654,
      "mean_band_width": 0.03860368925361004,
      "width_percentiles": {
        "p10": 0.02113095068244797,
        "p50": 0.04202753037160624,
        "p90": 0.04977806799857467
      },
      "width_by_fpr_region": {
        "0-10": 0.055247313846861046,
        "10-30": 0.04934259999757576,
        "30-50": 0.042794545635297894,
        "50-70": 0.03443831114411354,
        "70-90": 0.027813771958589553,
        "90-100": 0.021890133572433763
      },
      "violation_rate_by_region": {
        "0-10": 0.296,
        "10-30": 0.018,
        "30-50": 0.016,
        "50-70": 0.05,
        "70-90": 0.088,
        "90-100": 0.268
      },
      "mean_max_violation": 0.003105528894931974,
      "percentile_95_max_violation": 0.01832526143871994
    }
  },
  "HT_kde_calib": {
    "alpha_0.5": {
      "n_simulations": 500,
      "nominal_alpha": 0.5,
      "confidence_level": 0.5,
      "coverage_rate": 0.454,
      "coverage_se": 0.022265848288354075,
      "coverage_ci_lower": 0.4108757266738578,
      "coverage_ci_upper": 0.49782571264860515,
      "violation_rate_above": 0.218,
      "violation_rate_below": 0.462,
      "direction_test_pvalue": 3.286993901957587e-11,
      "mean_band_area": 0.03384450064588671,
      "std_band_area": 0.01310058202653388,
      "mean_band_width": 0.03385127090006673,
      "width_percentiles": {
        "p10": 0.016473261534364944,
        "p50": 0.03408117179490013,
        "p90": 0.04772926943347225
      },
      "width_by_fpr_region": {
        "0-10": 0.04853825195994264,
        "10-30": 0.04260680613959366,
        "30-50": 0.037083376109577716,
        "50-70": 0.030423731228232383,
        "70-90": 0.024916610921263693,
        "90-100": 0.019806093514560464
      },
      "violation_rate_by_region": {
        "0-10": 0.4,
        "10-30": 0.032,
        "30-50": 0.036,
        "50-70": 0.058,
        "70-90": 0.098,
        "90-100": 0.312
      },
      "mean_max_violation": 0.004699536161286923,
      "percentile_95_max_violation": 0.02616655380691651
    },
    "alpha_0.05": {
      "n_simulations": 500,
      "nominal_alpha": 0.05,
      "confidence_level": 0.95,
      "coverage_rate": 0.698,
      "coverage_se": 0.02053270561811083,
      "coverage_ci_lower": 0.6563723120570819,
      "coverage_ci_upper": 0.7366084491201434,
      "violation_rate_above": 0.11,
      "violation_rate_below": 0.284,
      "direction_test_pvalue": 4.688348939958478e-10,
      "mean_band_area": 0.05959919976738507,
      "std_band_area": 0.027210305678591264,
      "mean_band_width": 0.05961112199178343,
      "width_percentiles": {
        "p10": 0.02842000245691765,
        "p50": 0.05690601667964768,
        "p90": 0.09169447309916769
      },
      "width_by_fpr_region": {
        "0-10": 0.0881114252897245,
        "10-30": 0.07559668367061005,
        "30-50": 0.06484356786540524,
        "50-70": 0.05298277425599098,
        "70-90": 0.04333520522928238,
        "90-100": 0.03429551930294303
      },
      "violation_rate_by_region": {
        "0-10": 0.16,
        "10-30": 0.01,
        "30-50": 0.016,
        "50-70": 0.044,
        "70-90": 0.082,
        "90-100": 0.214
      },
      "mean_max_violation": 0.0010891129989026576,
      "percentile_95_max_violation": 0.00496383210898478
    }
  },
  "HT_kde_wilson": {
    "alpha_0.5": {
      "n_simulations": 500,
      "nominal_alpha": 0.5,
      "confidence_level": 0.5,
      "coverage_rate": 0.446,
      "coverage_se": 0.022229889788300795,
      "coverage_ci_lower": 0.4030063915853302,
      "coverage_ci_upper": 0.4898170371845176,
      "violation_rate_above": 0.206,
      "violation_rate_below": 0.412,
      "direction_test_pvalue": 4.746261867146163e-09,
      "mean_band_area": 0.03070747201559075,
      "std_band_area": 0.008711400546461879,
      "mean_band_width": 0.03071357839796545,
      "width_percentiles": {
        "p10": 0.016805207951113232,
        "p50": 0.033424027030142085,
        "p90": 0.0395879275686957
      },
      "width_by_fpr_region": {
        "0-10": 0.0439541994814833,
        "10-30": 0.039244805492403244,
        "30-50": 0.03403856249464303,
        "50-70": 0.02739851392734051,
        "70-90": 0.02213940931499004,
        "90-100": 0.017443414719280848
      },
      "violation_rate_by_region": {
        "0-10": 0.384,
        "10-30": 0.03,
        "30-50": 0.02,
        "50-70": 0.03,
        "70-90": 0.062,
        "90-100": 0.22
      },
      "mean_max_violation": 0.005417292234401915,
      "percentile_95_max_violation": 0.026289027027137594
    },
    "alpha_0.05": {
      "n_simulations": 500,
      "nominal_alpha": 0.05,
      "confidence_level": 0.95,
      "coverage_rate": 0.702,
      "coverage_se": 0.020454632727086548,
      "coverage_ci_lower": 0.6604929783319653,
      "coverage_ci_upper": 0.7404267881215676,
      "violation_rate_above": 0.102,
      "violation_rate_below": 0.202,
      "direction_test_pvalue": 6.125036446267331e-05,
      "mean_band_area": 0.038624742971992455,
      "std_band_area": 0.010941499574222942,
      "mean_band_width": 0.03863233678149347,
      "width_percentiles": {
        "p10": 0.021130951529003236,
        "p50": 0.0420409388586845,
        "p90": 0.04977806799857467
      },
      "width_by_fpr_region": {
        "0-10": 0.055262618455197456,
        "10-30": 0.04934590094995442,
        "30-50": 0.04280369937558473,
        "50-70": 0.03446195669043064,
        "70-90": 0.027867229548573492,
        "90-100": 0.02198459552314705
      },
      "violation_rate_by_region": {
        "0-10": 0.212,
        "10-30": 0.01,
        "30-50": 0.0,
        "50-70": 0.008,
        "70-90": 0.01,
        "90-100": 0.078
      },
      "mean_max_violation": 0.0030761703525711993,
      "percentile_95_max_violation": 0.01832526143871994
    }
  },
  "HT_kde_calib_wilson": {
    "alpha_0.5": {
      "n_simulations": 500,
      "nominal_alpha": 0.5,
      "confidence_level": 0.5,
      "coverage_rate": 0.526,
      "coverage_se": 0.022330427671677047,
      "coverage_ci_lower": 0.4822016483694956,
      "coverage_ci_upper": 0.5694018859265038,
      "violation_rate_above": 0.16,
      "violation_rate_below": 0.37,
      "direction_test_pvalue": 9.576512935440095e-11,
      "mean_band_area": 0.03385756544387904,
      "std_band_area": 0.01311242996399224,
      "mean_band_width": 0.0338642987047865,
      "width_percentiles": {
        "p10": 0.01637244182459043,
        "p50": 0.033858912569757794,
        "p90": 0.04709199104511376
      },
      "width_by_fpr_region": {
        "0-10": 0.04854690477824389,
        "10-30": 0.04261818379744872,
        "30-50": 0.037091399602048096,
        "50-70": 0.030432140453338623,
        "70-90": 0.024934771928548812,
        "90-100": 0.019836481123865244
      },
      "violation_rate_by_region": {
        "0-10": 0.342,
        "10-30": 0.026,
        "30-50": 0.022,
        "50-70": 0.034,
        "70-90": 0.044,
        "90-100": 0.172
      },
      "mean_max_violation": 0.0046839101679528984,
      "percentile_95_max_violation": 0.026044585831710966
    },
    "alpha_0.05": {
      "n_simulations": 500,
      "nominal_alpha": 0.05,
      "confidence_level": 0.95,
      "coverage_rate": 0.902,
      "coverage_se": 0.013296315279053816,
      "coverage_ci_lower": 0.8727939491335183,
      "coverage_ci_upper": 0.9250760811353939,
      "violation_rate_above": 0.022,
      "violation_rate_below": 0.076,
      "direction_test_pvalue": 0.00014197068519905542,
      "mean_band_area": 0.059629900468739123,
      "std_band_area": 0.027213192004996653,
      "mean_band_width": 0.05964162264366266,
      "width_percentiles": {
        "p10": 0.028418323387501596,
        "p50": 0.0566541914475825,
        "p90": 0.09126531160899531
      },
      "width_by_fpr_region": {
        "0-10": 0.0879921243001045,
        "10-30": 0.07555432740665123,
        "30-50": 0.06487927241992951,
        "50-70": 0.05303571090233326,
        "70-90": 0.04342808563601971,
        "90-100": 0.0344452586361986
      },
      "violation_rate_by_region": {
        "0-10": 0.076,
        "10-30": 0.0,
        "30-50": 0.0,
        "50-70": 0.002,
        "70-90": 0.0,
        "90-100": 0.02
      },
      "mean_max_violation": 0.0010463848196872428,
      "percentile_95_max_violation": 0.005604430365355619
    }
  },
  "ellipse_envelope_sweep": {
    "alpha_0.5": {
      "n_simulations": 500,
      "nominal_alpha": 0.5,
      "confidence_level": 0.5,
      "coverage_rate": 0.452,
      "coverage_se": 0.022257403262734853,
      "coverage_ci_lower": 0.4089073378092892,
      "coverage_ci_upper": 0.49582459887502,
      "violation_rate_above": 0.312,
      "violation_rate_below": 0.38,
      "direction_test_pvalue": 0.07589619277733246,
      "mean_band_area": 0.010283389547240718,
      "std_band_area": 0.0031951614099550913,
      "mean_band_width": 0.010285446636568033,
      "width_percentiles": {
        "p10": 0.005196998983317553,
        "p50": 0.011278328934960495,
        "p90": 0.013440651430558934
      },
      "width_by_fpr_region": {
        "0-10": 0.013978508981365255,
        "10-30": 0.013406001256993188,
        "30-50": 0.011493339819848538,
        "50-70": 0.009276711358189584,
        "70-90": 0.007454295947909357,
        "90-100": 0.005583522679800997
      },
      "violation_rate_by_region": {
        "0-10": 0.298,
        "10-30": 0.312,
        "30-50": 0.298,
        "50-70": 0.312,
        "70-90": 0.334,
        "90-100": 0.388
      },
      "mean_max_violation": 0.0015744605152517273,
      "percentile_95_max_violation": 0.006928069809405704
    },
    "alpha_0.05": {
      "n_simulations": 500,
      "nominal_alpha": 0.05,
      "confidence_level": 0.95,
      "coverage_rate": 0.844,
      "coverage_se": 0.01622738426241272,
      "coverage_ci_lower": 0.809585245166297,
      "coverage_ci_upper": 0.8731692085961551,
      "violation_rate_above": 0.04,
      "violation_rate_below": 0.144,
      "direction_test_pvalue": 4.606251020832626e-08,
      "mean_band_area": 0.02173537200584865,
      "std_band_area": 0.006748315612684345,
      "mean_band_width": 0.021739719949838615,
      "width_percentiles": {
        "p10": 0.010913922658417792,
        "p50": 0.024051794679814945,
        "p90": 0.028343629215831494
      },
      "width_by_fpr_region": {
        "0-10": 0.029403974816724812,
        "10-30": 0.028434327888831722,
        "30-50": 0.02443127130694687,
        "50-70": 0.019595311491131782,
        "70-90": 0.01566250667977333,
        "90-100": 0.011679551405583076
      },
      "violation_rate_by_region": {
        "0-10": 0.014,
        "10-30": 0.018,
        "30-50": 0.02,
        "50-70": 0.022,
        "70-90": 0.058,
        "90-100": 0.114
      },
      "mean_max_violation": 7.108083751860716e-05,
      "percentile_95_max_violation": 1.4456111296912143e-08
    }
  },
  "ellipse_envelope_quartic": {
    "alpha_0.5": {
      "n_simulations": 500,
      "nominal_alpha": 0.5,
      "confidence_level": 0.5,
      "coverage_rate": 0.398,
      "coverage_se": 0.02189045454073533,
      "coverage_ci_lower": 0.35602997790389446,
      "coverage_ci_upper": 0.4415253875502624,
      "violation_rate_above": 0.306,
      "violation_rate_below": 0.42,
      "direction_test_pvalue": 0.0032354375042357364,
      "mean_band_area": 0.02112679231149105,
      "std_band_area": 0.009782579114665698,
      "mean_band_width": 0.02113101851519409,
      "width_percentiles": {
        "p10": 0.00872935920599541,
        "p50": 0.02050434867902669,
        "p90": 0.035132682655520095
      },
      "width_by_fpr_region": {
        "0-10": 0.016426465215192455,
        "10-30": 0.023436993563010572,
        "30-50": 0.026085819528341294,
        "50-70": 0.024053876673460012,
        "70-90": 0.01844618964982033,
        "90-100": 0.010774150768915813
      },
      "violation_rate_by_region": {
        "0-10": 0.45,
        "10-30": 0.146,
        "30-50": 0.068,
        "50-70": 0.056,
        "70-90": 0.094,
        "90-100": 0.26
      },
      "mean_max_violation": 0.0022270365511670056,
      "percentile_95_max_violation": 0.009271661695920535
    },
    "alpha_0.05": {
      "n_simulations": 500,
      "nominal_alpha": 0.05,
      "confidence_level": 0.95,
      "coverage_rate": 0.762,
      "coverage_se": 0.01904499934365974,
      "coverage_ci_lower": 0.7227638647789387,
      "coverage_ci_upper": 0.797240980819208,
      "violation_rate_above": 0.062,
      "violation_rate_below": 0.184,
      "direction_test_pvalue": 3.3173529174399884e-08,
      "mean_band_area": 0.04409745336258763,
      "std_band_area": 0.020383756504496305,
      "mean_band_width": 0.044106274617511126,
      "width_percentiles": {
        "p10": 0.018145216519797964,
        "p50": 0.04278113040942673,
        "p90": 0.07303248393008605
      },
      "width_by_fpr_region": {
        "0-10": 0.03414242476752174,
        "10-30": 0.04873648007496081,
        "30-50": 0.05408319226424396,
        "50-70": 0.05011488554978371,
        "70-90": 0.03908794927608967,
        "90-100": 0.022741611305587068
      },
      "violation_rate_by_region": {
        "0-10": 0.12,
        "10-30": 0.016,
        "30-50": 0.01,
        "50-70": 0.008,
        "70-90": 0.028,
        "90-100": 0.108
      },
      "mean_max_violation": 0.00041099885011362694,
      "percentile_95_max_violation": 0.0024164866868337086
    }
  },
  "logit_max_modulus": {
    "alpha_0.5": {
      "n_simulations": 500,
      "nominal_alpha": 0.5,
      "confidence_level": 0.5,
      "coverage_rate": 0.746,
      "coverage_se": 0.019467100451787882,
      "coverage_ci_lower": 0.7060690794081029,
      "coverage_ci_upper": 0.7821797450848135,
      "violation_rate_above": 0.158,
      "violation_rate_below": 0.126,
      "direction_test_pvalue": 0.20795842151862862,
      "mean_band_area": 0.10792147522774043,
      "std_band_area": 0.11292895291747113,
      "mean_band_width": 0.10781374211403498,
      "width_percentiles": {
        "p10": 0.045552066303260516,
        "p50": 0.07731885504879983,
        "p90": 0.15936601912588227
      },
      "width_by_fpr_region": {
        "0-10": 0.10534256853729042,
        "10-30": 0.0971335188007366,
        "30-50": 0.09816523292017178,
        "50-70": 0.10339274702852105,
        "70-90": 0.12003522735249542,
        "90-100": 0.13743681652449785
      },
      "violation_rate_by_region": {
        "0-10": 0.216,
        "10-30": 0.01,
        "30-50": 0.014,
        "50-70": 0.002,
        "70-90": 0.0,
        "90-100": 0.062
      },
      "mean_max_violation": 0.00212128027661879,
      "percentile_95_max_violation": 0.012465638867163547
    },
    "alpha_0.05": {
      "n_simulations": 500,
      "nominal_alpha": 0.05,
      "confidence_level": 0.95,
      "coverage_rate": 0.954,
      "coverage_se": 0.009368457717255283,
      "coverage_ci_lower": 0.9319222072317267,
      "coverage_ci_upper": 0.9691548916291838,
      "violation_rate_above": 0.004,
      "violation_rate_below": 0.042,
      "direction_test_pvalue": 6.604194641113281e-05,
      "mean_band_area": 0.16459583001998424,
      "std_band_area": 0.14385509829093104,
      "mean_band_width": 0.16444617054684332,
      "width_percentiles": {
        "p10": 0.06715105743141699,
        "p50": 0.123022220380102,
        "p90": 0.29222026563113757
      },
      "width_by_fpr_region": {
        "0-10": 0.16438392130016752,
        "10-30": 0.14559456621997288,
        "30-50": 0.1457111551522275,
        "50-70": 0.1543398561383578,
        "70-90": 0.18257519684803153,
        "90-100": 0.22650530664171487
      },
      "violation_rate_by_region": {
        "0-10": 0.042,
        "10-30": 0.0,
        "30-50": 0.0,
        "50-70": 0.0,
        "70-90": 0.0,
        "90-100": 0.004
      },
      "mean_max_violation": 0.00032140305860969923,
      "percentile_95_max_violation": 8.327172442511039e-11
    }
  },
  "pointwise": {
    "alpha_0.5": {
      "n_simulations": 500,
      "nominal_alpha": 0.5,
      "confidence_level": 0.5,
      "coverage_rate": 0.0,
      "coverage_se": 0.0,
      "coverage_ci_lower": 4.336808689942018e-19,
      "coverage_ci_upper": 0.007624340461552241,
      "violation_rate_above": 0.876,
      "violation_rate_below": 0.936,
      "direction_test_pvalue": 0.33531974904667755,
      "mean_band_area": 0.00777060719662222,
      "std_band_area": 0.0021723864484287448,
      "mean_band_width": 0.007741610299442447,
      "width_percentiles": {
        "p10": 0.004215713755372382,
        "p50": 0.00841646382972204,
        "p90": 0.010004327138273622
      },
      "width_by_fpr_region": {
        "0-10": 0.01186262813654577,
        "10-30": 0.009868371674712311,
        "30-50": 0.00854314928227663,
        "50-70": 0.006881770425915718,
        "70-90": 0.0055677532989978785,
        "90-100": 0.0044179707168343066
      },
      "violation_rate_by_region": {
        "0-10": 0.998,
        "10-30": 0.826,
        "30-50": 0.774,
        "50-70": 0.776,
        "70-90": 0.852,
        "90-100": 0.962
      },
      "mean_max_violation": 0.018075957085216532,
      "percentile_95_max_violation": 0.04442934044475629
    },
    "alpha_0.05": {
      "n_simulations": 500,
      "nominal_alpha": 0.05,
      "confidence_level": 0.95,
      "coverage_rate": 0.276,
      "coverage_se": 0.01999119806314769,
      "coverage_ci_lower": 0.23863813294339814,
      "coverage_ci_upper": 0.31677757158337744,
      "violation_rate_above": 0.342,
      "violation_rate_below": 0.574,
      "direction_test_pvalue": 6.608848513351324e-08,
      "mean_band_area": 0.02250205252326558,
      "std_band_area": 0.00634273236013647,
      "mean_band_width": 0.02247350081933628,
      "width_percentiles": {
        "p10": 0.012201560976791917,
        "p50": 0.024399407103636854,
        "p90": 0.029035911440690853
      },
      "width_by_fpr_region": {
        "0-10": 0.033284106140600726,
        "10-30": 0.028652057227652548,
        "30-50": 0.024816373057946563,
        "50-70": 0.019998796525716782,
        "70-90": 0.01614464997935295,
        "90-100": 0.012817494562524045
      },
      "violation_rate_by_region": {
        "0-10": 0.48,
        "10-30": 0.132,
        "30-50": 0.118,
        "50-70": 0.144,
        "70-90": 0.2,
        "90-100": 0.438
      },
      "mean_max_violation": 0.0062668204096625185,
      "percentile_95_max_violation": 0.03000696016883874
    }
  },
  "ks": {
    "alpha_0.5": {
      "n_simulations": 500,
      "nominal_alpha": 0.5,
      "confidence_level": 0.5,
      "coverage_rate": 0.978,
      "coverage_se": 0.006559878047646925,
      "coverage_ci_lower": 0.9610391387886836,
      "coverage_ci_upper": 0.9876719917300725,
      "violation_rate_above": 0.01,
      "violation_rate_below": 0.012,
      "direction_test_pvalue": 1.0,
      "mean_band_area": 0.04774617496749157,
      "std_band_area": 0.0036550653787277487,
      "mean_band_width": 0.047703001244888944,
      "width_percentiles": {
        "p10": 0.04333127343543103,
        "p50": 0.04749469252336695,
        "p90": 0.05275596302008444
      },
      "width_by_fpr_region": {
        "0-10": 0.132707486963219,
        "10-30": 0.04644257445907238,
        "30-50": 0.03855658774360269,
        "50-70": 0.034069007381916046,
        "70-90": 0.03244992157304287,
        "90-100": 0.04216090182130208
      },
      "violation_rate_by_region": {
        "0-10": 0.0,
        "10-30": 0.014,
        "30-50": 0.014,
        "50-70": 0.008,
        "70-90": 0.004,
        "90-100": 0.002
      },
      "mean_max_violation": 6.231155281689782e-05,
      "percentile_95_max_violation": 0.0
    },
    "alpha_0.05": {
      "n_simulations": 500,
      "nominal_alpha": 0.05,
      "confidence_level": 0.95,
      "coverage_rate": 1.0,
      "coverage_se": 0.0,
      "coverage_ci_lower": 0.9923756595384479,
      "coverage_ci_upper": 1.0,
      "violation_rate_above": 0.0,
      "violation_rate_below": 0.0,
      "direction_test_pvalue": 1.0,
      "mean_band_area": 0.07085687723209765,
      "std_band_area": 0.005754434221304436,
      "mean_band_width": 0.07081408556243397,
      "width_percentiles": {
        "p10": 0.0641655394043248,
        "p50": 0.07059640609680184,
        "p90": 0.07851723078610835
      },
      "width_by_fpr_region": {
        "0-10": 0.19397747516628805,
        "10-30": 0.0698696081918483,
        "30-50": 0.05786321270407736,
        "50-70": 0.05096042334592342,
        "70-90": 0.048354121066570284,
        "90-100": 0.06094422295969166
      },
      "violation_rate_by_region": {
        "0-10": 0.0,
        "10-30": 0.0,
        "30-50": 0.0,
        "50-70": 0.0,
        "70-90": 0.0,
        "90-100": 0.0
      },
      "mean_max_violation": 0.0,
      "percentile_95_max_violation": 0.0
    }
  },
  "working_hotelling": {
    "alpha_0.5": {
      "n_simulations": 500,
      "nominal_alpha": 0.5,
      "confidence_level": 0.5,
      "coverage_rate": 0.462,
      "coverage_se": 0.022296008611408458,
      "coverage_ci_lower": 0.41875629515879303,
      "coverage_ci_upper": 0.505823154716285,
      "violation_rate_above": 0.314,
      "violation_rate_below": 0.368,
      "direction_test_pvalue": 0.15903737868267004,
      "mean_band_area": 0.010523958170575713,
      "std_band_area": 0.003257232223971149,
      "mean_band_width": 0.010512082898451193,
      "width_percentiles": {
        "p10": 0.005261239903668067,
        "p50": 0.011658008090769022,
        "p90": 0.013696525602523782
      },
      "width_by_fpr_region": {
        "0-10": 0.014485551823028148,
        "10-30": 0.013769507873139134,
        "30-50": 0.011836475538134576,
        "50-70": 0.00946903901565075,
        "70-90": 0.007556154151439667,
        "90-100": 0.005637526417016982
      },
      "violation_rate_by_region": {
        "0-10": 0.29,
        "10-30": 0.274,
        "30-50": 0.266,
        "50-70": 0.284,
        "70-90": 0.322,
        "90-100": 0.378
      },
      "mean_max_violation": 0.0013240853965383677,
      "percentile_95_max_violation": 0.006483527127982218
    },
    "alpha_0.05": {
      "n_simulations": 500,
      "nominal_alpha": 0.05,
      "confidence_level": 0.95,
      "coverage_rate": 0.846,
      "coverage_se": 0.016142118820031033,
      "coverage_ci_lower": 0.811734636678946,
      "coverage_ci_upper": 0.8749893197216598,
      "violation_rate_above": 0.042,
      "violation_rate_below": 0.14,
      "direction_test_pvalue": 2.509086976240059e-07,
      "mean_band_area": 0.02186408737136608,
      "std_band_area": 0.0067779563303234135,
      "mean_band_width": 0.02185431065873838,
      "width_percentiles": {
        "p10": 0.010944877606340591,
        "p50": 0.02423714972867224,
        "p90": 0.028471767873595594
      },
      "width_by_fpr_region": {
        "0-10": 0.029813662913984906,
        "10-30": 0.028622073112095886,
        "30-50": 0.024605257147818804,
        "50-70": 0.019688235086679464,
        "70-90": 0.015712496768832206,
        "90-100": 0.011725200902700423
      },
      "violation_rate_by_region": {
        "0-10": 0.014,
        "10-30": 0.018,
        "30-50": 0.02,
        "50-70": 0.022,
        "70-90": 0.052,
        "90-100": 0.114
      },
      "mean_max_violation": 6.681498689040955e-05,
      "percentile_95_max_violation": 1.473514913974403e-08
    }
  },
  "metadata": {
    "dgp_type": "hetero_gaussian",
    "n_total": 10000,
    "n_pos": 5000,
    "n_neg": 5000,
    "prevalence": 0.5,
    "timestamp": "20260103",
    "n_lhs_combinations": 500,
    "n_simulations_per_lhs": 1
  }
}